logger_hub_drh/__init__.py
logger_hub_drh/logger_utils.py
logger_hub_drh-0.1.0.dist-info/WHEEL
logger_hub_drh-0.1.0.dist-info/METADATA
logger_hub_drh-0.1.0.dist-info/RECORD
