Metadata-Version: 2.1
Name: logger-hub-drh
Version: 0.1.0
Summary: 
Author: daniel-rodriguez-hernandez
Author-email: daniel.rodriguez.hernandez@pwc.com
Requires-Python: >=3.10,<4.0
Classifier: Programming Language :: Python :: 3
Classifier: Programming Language :: Python :: 3.10
Requires-Dist: requests (>=2.28.1,<3.0.0)
